{
    "AspNetStateService.AspNetCore": {
        "Store": "Amazon.S3"
    },
    "AspNetStateService.EntityFrameworkCore": {
        "Provider": "InMemory"
    },
    "AspNetStateService.Azure.Storage.Table": {
        "ConnectionString": "UseDevelopmentStorage=true",
        "TableName": "state"
    },
    "AspNetStateService.Azure.Storage.Blob": {
        "ConnectionString": "UseDevelopmentStorage=true",
        "ContainerName": "state"
    },
    "AspNetStateService.MongoDB": {
        "ConnectionString": "mongodb://localhost:27017"
    },
    "AspNetStateService.Redis": {
        "Configuration": "localhost"
    },
    "AspNetStateService.Amazon.S3": {
        "AwsAccessKeyId": "AKIAJ7MOHJMFKWI3VETA",
        "AwsSecretAccessKey": "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",
        "RegionEndpointName": "us-east-1",
        "BucketName": "cogito-test"
    }
}
